session_cleanup/__init__.py
session_cleanup/models.py
session_cleanup/settings.py
session_cleanup/tasks.py
django_session_cleanup-4.0.0.dist-info/LICENSE
django_session_cleanup-4.0.0.dist-info/METADATA
django_session_cleanup-4.0.0.dist-info/WHEEL
django_session_cleanup-4.0.0.dist-info/top_level.txt
django_session_cleanup-4.0.0.dist-info/RECORD
