Metadata-Version: 2.1
Name: django-session-cleanup
Version: 4.0.0
Summary: A periodic task for removing expired Django sessions with Celery.
Home-page: https://github.com/mobolic/django-session-cleanup
Author: Elijah Rutschman
Author-email: elijahr+django-session-cleanup@gmail.com
Maintainer: Martey Dodoo
Maintainer-email: martey+django-session-cleanup@mobolic.com
License: UNKNOWN
Platform: UNKNOWN
Classifier: Framework :: Django :: 2.2
Classifier: Framework :: Django :: 3.0
Classifier: Framework :: Django :: 3.1
Classifier: License :: OSI Approved :: BSD License
Classifier: Programming Language :: Python :: 3.5
Classifier: Programming Language :: Python :: 3.6
Classifier: Programming Language :: Python :: 3.7
Classifier: Programming Language :: Python :: 3.8
Classifier: Programming Language :: Python :: 3.9
